[
  {
    "version": 111,
    "changes": [
      {
        "type": "Neu/Endlich",
        "change": "In Videos vor und zurück spulen."
      },
      {
        "type": "Fix",
        "change": "Vollbild für Videos ist nun echtes Vollbild."
      },
      {
        "type": "Fix",
        "change": "Bugfix beim Wechsel in den Vollbild."
      }
    ]
  },
  {
    "version": 110,
    "changes": [
      {
        "type": "Neu",
        "change": "Suche nach Qualität (q:hd), Datum (d:2015) und repost (f:repost), siehe auch: https://github.com/mopsalarm/pr0gramm-tags/blob/master/README.md"
      },
      {
        "type": "Fix",
        "change": "Bessere Meldungen im Falle einiger Fehler"
      },
      {
        "type": "Fix",
        "change": "Bugfixes"
      }
    ]
  },
  {
    "version": 109,
    "changes": [
      {
        "type": "Neu",
        "change": "Video beginnt beim Drehen des Geräts nicht wieder von vorne"
      },
      {
        "type": "Neu",
        "change": "Willkommensbildschirm um eine Standardauswahl von Lesezeichen und Menueinträgen zu ermöglichen. Auch unter Einstellungen zu finden."
      },
      {
        "type": "Fix",
        "change": "Erlaube nun auch Umlaute in dem 'Erweiterte Suche'-Dialog"
      },
      {
        "type": "Fix",
        "change": "'Erweiterte Suche'-Dialog verbessert"
      }
    ]
  },
  {
    "version": 108,
    "changes": [
      {
        "type": "Neu",
        "change": "Erweiterte Suche Dialog im Menü"
      },
      {
        "type": "Neu",
        "change": "Es können nun alle Kategorien durchsucht werden. Suche in den Extra-Kategorien (nicht top/new) ist nun mächtiger. Unterstützt werden nun logische Ausdrücke wie 'webm -sound', 'porn -süßvieh -0815' oder 'erdogan | trump'. Wer mutig ist, kann new/top durchsuchen, indem er ein Fragezeichen an den Anfrang der Suche stellt: '? gif|webm-sound'. Mehr Informationen und User-Script für den Browser auf https://github.com/mopsalarm/pr0gramm-tags/blob/master/README.md"
      },
      {
        "type": "Neu",
        "change": "Passwortwiederherstellen Funktion über die App"
      },
      {
        "type": "Neu",
        "change": "Erlaube die neuen Uploadgrößen"
      },
      {
        "type": "Neu",
        "change": "Kompatibilitätseinstellung um die Videodarstellung eine SurfaceView zu verwenden"
      },
      {
        "type": "Fix",
        "change": "Rechtschreibfehler"
      }
    ]
  },
  {
    "version": 107,
    "changes": [
      {
        "type": "Neu",
        "change": "Im Login Bildschim gibts nun einen Button zum Registrieren."
      },
      {
        "type": "Neu",
        "change": "Testweise 'Text' Kategorie - ich verspreche nichts, ist vielleicht morgen wieder raus."
      },
      {
        "type": "Neu",
        "change": "Kontaktformular erweitert."
      },
      {
        "type": "Fix",
        "change": "Beim Start der App wird wieder der richtige Content/Filter angezeigt."
      },
      {
        "type": "Intern",
        "change": "Interne Umbauten!"
      }
    ]
  },
  {
    "version": 106,
    "changes": [
      {
        "type": "Neu",
        "change": "Anzahl der ungelesenen Nachrichten wird in Launchern am Icon angezeigt, die es unterstützen."
      },
      {
        "type": "Fix",
        "change": "/stelz/ Links werden jetzt korrekt in der App geöffnet."
      },
      {
        "type": "Fix",
        "change": "Die eigenen Favoriten werden nicht als 'gesehen' markiert."
      },
      {
        "type": "Fix",
        "change": "Fehlerhafte 'repost' Anzeige im Feed behoben."
      },
      {
        "type": "Intern",
        "change": "Ein paar interne Änderung in Bezug auf Login und favorisierte Kommentare."
      }
    ]
  },
  {
    "version": 105,
    "changes": [
      {
        "type": "Neu",
        "change": "Kompatibilitätseinstellungen erweitert - bei Video- und Audioproblemen dort schauen!"
      },
      {
        "type": "Fix",
        "change": "Beim Abspielen von Videos mit Sound gab es manchmal ein kurzes Geräusch, obwohl diese auf Stumm geschaltet waren."
      },
      {
        "type": "Fix",
        "change": "Fix Sound/kein Sound in im Quickpreview."
      },
      {
        "type": "Fix",
        "change": "Fehler und Info-Dialoge wurden teilweise nicht korrekt angezeigt."
      },
      {
        "type": "Fix",
        "change": "Der 'warten'-Dialog beim Absenden von Feedback wird wieder korrekt geschlossen."
      },
      {
        "type": "Fix",
        "change": "Am PC gevotete Posts werden nun automatisch in der App als gesehen markiert."
      }
    ]
  },
  {
    "version": 104,
    "changes": [
      {
        "type": "Fix",
        "change": "Sorry, wichtige Bugfixes, für mehr Info, siehe das vorige Release."
      }
    ]
  },
  {
    "version": 103,
    "changes": [
      {
        "type": "INFO - BITTE LESEN",
        "change": "Diese Version hat einen neuen Video Player. Wenn du Probleme bei der Videowiedergabe hast, probiere bitte die Kompatibilitätseinstellungen."
      },
      {
        "type": "Neu",
        "change": "Zeige den Fortschritt beim Buffern eines Videos im Fortschrittsbalken."
      },
      {
        "type": "Fix",
        "change": "Videowiedergabe verbessert, sollte nun auf allen Geräten (ab Jellybean) stabiler laufen"
      },
      {
        "type": "Fix",
        "change": "Kompatibilitätseinstellungen für Videocodec Auswahl wieder da."
      },
      {
        "type": "Fix",
        "change": "Ton wird automatisch auf leise gestellt, sobald ein Anruf eingeht."
      },
      {
        "type": "Fix",
        "change": "Update auf Android N gefixt."
      }
    ]
  },
  {
    "version": 102,
    "changes": [
      {
        "type": "Neu",
        "change": "Favoriten können nun auch durchsucht werden."
      },
      {
        "type": "Fix",
        "change": "Download von Videos ist wieder korrekt."
      },
      {
        "type": "Fix",
        "change": "Vorschaubildchen sind wieder da."
      },
      {
        "type": "Fix",
        "change": "Reposts werden im Feed wieder korrekt hervorgehoben."
      },
      {
        "type": "Fix",
        "change": "Probleme beim Abspielen vorgeladener Videos behoben."
      },
      {
        "type": "Fix",
        "change": "'Ton Aus'-Button vergrößert."
      },
      {
        "type": "Fix",
        "change": "Vorschläge beim Tippen von @username gehen wieder."
      },
      {
        "type": "Fix",
        "change": "Kommentare unter langen Bildern werden wieder korrekt angezeigt."
      }
    ]
  },
  {
    "version": 101,
    "changes": [
      {
        "type": "Neu",
        "change": "Sound."
      }
    ]
  },
  {
    "version": 100,
    "changes": [
      {
        "type": "Fix",
        "change": "Liste der Tag-Vorschläge aktualisiert."
      },
      {
        "type": "Fix",
        "change": "Noch mehr API Änderungen."
      }
    ]
  },
  {
    "version": 99,
    "changes": [
      {
        "type": "Fix",
        "change": "API Änderungen zum syncen der Votes implementiert."
      },
      {
        "type": "Fix",
        "change": "Fehlermeldungen für einige Netzwerkprobleme und fürs Ratelimit verbessert."
      },
      {
        "type": "Fix",
        "change": "Links auf www.pr0gramm.com wurden versehentlich im Incognito-Browser geöffnet. @JoeNaendi ob du behindert bist?"
      }
    ]
  },
  {
    "version": 98,
    "changes": [
      {
        "type": "Fix",
        "change": "Zur Seite wischen sollte nicht mehr nach ein paar Posts aufhören."
      }
    ]
  },
  {
    "version": 97,
    "changes": [
      {
        "type": "Fix",
        "change": "Votes verschwinden nicht mehr zufällig"
      },
      {
        "type": "Fix",
        "change": "Verschiedene Bugfixes"
      }
    ]
  },
  {
    "version": 96,
    "changes": [
      {
        "type": "Fix",
        "change": "Workaround gegen 'Image failed to decode using JPEG decoder'."
      },
      {
        "type": "Fix",
        "change": "Login stark beschleunigt."
      },
      {
        "type": "Fix",
        "change": "Zweifinger-Zoom geht nun im integrierten Browser."
      }
    ]
  },
  {
    "version": 95,
    "changes": [
      {
        "type": "Neu",
        "change": "Du kannst nun jemanden aus der App heraus stelzen."
      },
      {
        "type": "Neu",
        "change": "Einstellung um YouTube und Vimeo Links trotz Incognito Browser in der entsprechenden App zu starten"
      },
      {
        "type": "Fix",
        "change": "Caching für die Thumbnails im Feed verbessert."
      },
      {
        "type": "Fix",
        "change": "Fehler bei der Anzeige von +/- bei Votes behoben."
      },
      {
        "type": "Fix",
        "change": "Scrollen in der Navigation verbessert."
      },
      {
        "type": "Fix",
        "change": "Incognito Browser beachtet nun die Rotationseinstellung vom System."
      }
    ]
  },
  {
    "version": 94,
    "changes": [
      {
        "type": "Neu",
        "change": "Incognito Browser in die App integriert. Aktivierbar unter Einstellungen -> Verhalten."
      },
      {
        "type": "Neu",
        "change": "Invites können aus der App heraus verschickt und angezeigt werden."
      },
      {
        "type": "Fix",
        "change": "In den privaten Nachrichten wird nun der richtige Punkt des Unterhaltungspartners angezeigt."
      },
      {
        "type": "Fix",
        "change": "Fehlerhaftes automatisches Aktivieren von 'sfw' behoben."
      }
    ]
  },
  {
    "version": 93,
    "changes": [
      {
        "type": "Neu",
        "change": "Optional einstellbar, dass die App immer in 'sfw' gestartet wird."
      },
      {
        "type": "Fix",
        "change": "'Automatisch HQ im Vollbild' funktioniert wieder."
      },
      {
        "type": "Fix",
        "change": "Healthcheck für Kategorien repariert."
      },
      {
        "type": "Fix",
        "change": "Ein paar Tippfehler behoben."
      },
      {
        "type": "Fix",
        "change": "Neuladen durch herunterwischen geht wieder."
      },
      {
        "type": "Fix",
        "change": "Laden von großen Bildern verbessert."
      }
    ]
  },
  {
    "version": 92,
    "changes": [
      {
        "type": "Neu",
        "change": "Kommentare zusammenklappbar (drei Punkte)."
      },
      {
        "type": "Neu",
        "change": "Links zu Posts und Kommentaren direkt aus der App heraus kopierbar (drei Punkte)."
      },
      {
        "type": "Fix",
        "change": "'Unexpected end of stream' Problem behoben."
      },
      {
        "type": "Fix",
        "change": "Lade-Indikator wird nun korrekt ausgeblendet, wenn eine HQ-Version geladen wurde."
      }
    ]
  },
  {
    "version": 91,
    "changes": [
      {
        "type": "Fix",
        "change": "Probleme beim Laden einiger Bilder behoben"
      },
      {
        "type": "Fix",
        "change": "Probleme beim Einloggen behoben"
      },
      {
        "type": "Fix",
        "change": "Unnötige Berechtigung wieder entfernt."
      }
    ]
  },
  {
    "version": 90,
    "changes": [
      {
        "type": "Neu",
        "change": "Endlich: Upload von .gif und .webm direkt vom Handy aus!"
      },
      {
        "type": "Neu",
        "change": "Repost Warnung in den Uploadprozess integriert."
      },
      {
        "type": "Fix",
        "change": "Webm-Softwaredekoder war versehentlich komplett deaktiviert - darum liefen Videos envt. langsamer als sonst."
      }
    ]
  },
  {
    "version": 89,
    "changes": [
      {
        "type": "Info",
        "change": "Dies ist in erster Linie ein Bugfixrelease."
      },
      {
        "type": "Neu",
        "change": "Anzeige von Info-Nachrichten beim Start (z.B. pr0gramm ist down.)"
      },
      {
        "type": "Fix",
        "change": "'App bleibt schwarz' Bug behoben!"
      },
      {
        "type": "Fix",
        "change": "Mehr Abstürze bei komischen Unicodezeichen in Kommentaren und Nachrichten verhindert."
      },
      {
        "type": "Fix",
        "change": "Bugfixes"
      }
    ]
  },
  {
    "version": 88,
    "changes": [
      {
        "type": "Neu",
        "change": "Wenn ein Bild vor dem Upload zu groß ist, kann die App das nun selbst verkleinern."
      },
      {
        "type": "Neu",
        "change": "Wenn ein Bild wegen falschen Filtereinstellungen aktuell nicht angezeigt werden kann, wirst du nun darüber informiert. Nach dem Ändern der Einstellungen, wird die App nochmal versuchen, das Bild zu öffnen."
      },
      {
        "type": "Neu",
        "change": "Lange auf den Benis eines Kommentars zeigt dessen up/down Votes an"
      },
      {
        "type": "Fix",
        "change": "Verschiedene Bugfixes"
      }
    ]
  },
  {
    "version": 87,
    "changes": [
      {
        "type": "Neu",
        "change": "Auf der Website gesetztes pr0mium Theme wird nach dem Einloggen eingestellt"
      },
      {
        "type": "Neu",
        "change": "Softwaredekoder wird nun automatisch aktiviert. Falls daraufhin ständig Fehler beim Abspielen von Videos auftreten, bitte Bescheid sagen"
      },
      {
        "type": "Neu",
        "change": "Benachrichtigungen verbessert. Sie können nun besser/normal 'als gelesen' markiert werden."
      },
      {
        "type": "Überarbeitet",
        "change": "Animationen überarbeitet."
      },
      {
        "type": "Fix",
        "change": "'Dies ist eine Beta'-Meldung nicht mehr anzeigen, wenn Beta nicht aktiv ist"
      },
      {
        "type": "Fix",
        "change": "Quickpeek wird beim Rotieren nun versteckt"
      },
      {
        "type": "Fix",
        "change": "Okay-Button beim Feedbackhinweis"
      }
    ]
  },
  {
    "version": 86,
    "changes": [
      {
        "type": "Neu",
        "change": "Instagram ähnliches 'quick-peek'. Im Feed etwas länger auf ein Vorschaubildchen drücken. Deaktivierbar unter Einstellungen/Verhalten."
      },
      {
        "type": "Neu",
        "change": "Navigation mithilfe der Lautstärketasten (Muss unter Einstellungen/Verhalten/Post aktiviert werden)"
      },
      {
        "type": "Fix",
        "change": "Lesezeichen löschen Dialog ist jetzt abbrechbar"
      },
      {
        "type": "Fix (Hoffentlich)",
        "change": "Text in den Kommentaren sollte auch unter Android 6 wieder markierbar sein."
      },
      {
        "type": "Fix",
        "change": "Autokorrektur sollte wieder beim Nachrichten/Kommentare schreiben funktionieren"
      },
      {
        "type": "Fix",
        "change": "Crash beim Drehen des Geräts während man 'quick-peek' offen hat."
      },
      {
        "type": "Fix",
        "change": "HTTPS workaround, da der Server kaputt ist."
      }
    ]
  },
  {
    "version": 85,
    "changes": [
      {
        "type": "Neu",
        "change": "Episches Blau Theme"
      }
    ]
  },
  {
    "version": 84,
    "changes": [
      {
        "type": "Neu",
        "change": "Themes"
      },
      {
        "type": "Fix",
        "change": "Ladeanimation bei Java-Dekoder"
      },
      {
        "type": "Fix",
        "change": "Wechsel automatisch vom Java-Dekoder auf den WEBM-Software Dekoder"
      }
    ]
  },
  {
    "version": 83,
    "changes": [
      {
        "type": "Neu",
        "change": "'musste scrollen' Blder sind nun schärfer! Vollbildmodus für Bilder ist auch verbessert. Falls es nun bei großen Bildern Abstürze gibt, bitte Bescheid geben!"
      },
      {
        "type": "Neu",
        "change": "Benisgraph wird nun nach dem Login mit deiner initialen Benishistory gefüllt."
      },
      {
        "type": "Neu",
        "change": "Videofortschrittsbalken nun auch mit Softwaredekoder."
      },
      {
        "type": "Neu",
        "change": "Menüeintrag im Feed um die gleiche Suche in 'top' oder 'neu' nochmal auszuführen."
      },
      {
        "type": "Neu",
        "change": "Dies ist nun die offizielle pr0gramm app. Wow!"
      },
      {
        "type": "Fix",
        "change": "Caching von Metainformationen verbessert"
      },
      {
        "type": "Fix",
        "change": "Bilder werden wieder komplett dargestellt"
      },
      {
        "type": "Fix",
        "change": "Benisgraph ist wieder da. Sorry!"
      },
      {
        "type": "Fix",
        "change": "Transitions wieder gefixt."
      },
      {
        "type": "Fix",
        "change": "Regeln sind nun nummeriert."
      }
    ]
  },
  {
    "version": 82,
    "changes": [
      {
        "type": "Neu",
        "change": "Bereits gesuchte Begriffe werden automatisch vorgeschlagen"
      },
      {
        "type": "Neu",
        "change": "Die List der gesuchten Begriffe kann wieder geleert werden (Einstellungen -> Visuell)"
      },
      {
        "type": "Neu",
        "change": "Regeln können jetzt, wenn du angemeldet bist, direkt über die Navigation aufgerufen werden"
      },
      {
        "type": "Neu",
        "change": "Bilder können in der Tabletansicht gezoomt werden"
      },
      {
        "type": "Fix",
        "change": "Absturz beim Anzeigen einiger verbockter Kommentare behoben"
      },
      {
        "type": "Fix",
        "change": "Layoutfixes"
      },
      {
        "type": "Fix",
        "change": "Fehlerbehandlung verbessert"
      },
      {
        "type": "Fix",
        "change": "Softwaredekoder jetzt auch auf 64 Bit Systemen und x86(_64) CPUs."
      },
      {
        "type": "Fix",
        "change": "Anzeige des Buffer-Indicators, wenn der Softwaredekoder nicht genug Daten hat."
      },
      {
        "type": "Fix",
        "change": "Der Text bei einem neuen Kommentar bleibt beim Rotieren erhalten."
      }
    ]
  },
  {
    "version": 81,
    "changes": [
      {
        "type": "Info",
        "change": "Dies ist nur ein Bugfix-Release. Sorry dafür!"
      },
      {
        "type": "Fix",
        "change": "Transparente Posts-Bug gefixt."
      },
      {
        "type": "Fix",
        "change": "Farben im sfw/nsfw-Wechselmenü korrigiert"
      }
    ]
  },
  {
    "version": 80,
    "changes": [
      {
        "type": "Neu",
        "change": "Kommentare können nun favorisiert werden. Läuft geräteübergreifend im Browser mittels Userscript von Mopsalarm."
      },
      {
        "type": "Neu",
        "change": "Autovervollständigung von Usernamen beim Verfassen von Kommentaren und Nachrichten"
      },
      {
        "type": "Neu",
        "change": "Alle Zusatzservices verwenden nun nur noch HTTPs"
      },
      {
        "type": "Neu",
        "change": "WIP: Experimentelles Layout für 10 Zoll Tablets! Feedback!?"
      }
    ]
  },
  {
    "version": 79,
    "changes": [
      {
        "type": "Neu",
        "change": "Zeige mehr Kommentare eines Users in der Useransicht an"
      },
      {
        "type": "Neu",
        "change": "Zeige Registrierdatum und Banndauer an"
      },
      {
        "type": "Fix",
        "change": "Fehler in den Benutzerinformationen beim Umschalten zwischen Kommentaren und Uploads behoben"
      },
      {
        "type": "Fix",
        "change": "Stabilität von Preloading verbessert, sollte nicht mehr abkacken"
      },
      {
        "type": "Fix",
        "change": "Benachrichtigung bei neuen Updates"
      },
      {
        "type": "Workaround",
        "change": "Text in Kommentaren markieren ist auf Android 6 erstmal deaktiviert. Das führte durch einen Bug in Android zum Absturz der App :/"
      },
      {
        "type": "Update",
        "change": "Liste mit Automatischen Tag-Vorschlägen upgedated"
      }
    ]
  },
  {
    "version": 78,
    "changes": [
      {
        "type": "Neu",
        "change": "Neue Option unter Kompatibilität um einen Proxy Server für Api-Anfragen zu nutzen. Kann helfen, wenn du im WLAN häufig Sachen nicht laden kannst."
      },
      {
        "type": "Neu",
        "change": "Videofortschritt bei Loops verstecken"
      },
      {
        "type": "Fix",
        "change": "Absturz beim Drehen des Telefons gefixt"
      },
      {
        "type": "Fix",
        "change": "Verstecke die 'repost'-Badge im Vollbild"
      },
      {
        "type": "Fix",
        "change": "Startup auf langsameren Geräten beschleunigt"
      },
      {
        "type": "Fix",
        "change": "Größe der App über 30% kleiner"
      },
      {
        "type": "Fix",
        "change": "Wenn man im Videovollbild zur Seite wischt, wird Vollbild verlassen"
      },
      {
        "type": "Entfernt",
        "change": "Muzei Support entfernt. Benutzt eh kaum einer"
      }
    ]
  },
  {
    "version": 77,
    "changes": [
      {
        "type": "Neu",
        "change": "Neue 'versteckte Benis'-Punkte. Sie sind nun etwas kleiner als vorher"
      },
      {
        "type": "Fix",
        "change": "Links mit Prozentzeichen funktionieren wieder"
      },
      {
        "type": "Fix",
        "change": "Scrollen in den Nachrichten sollte nun besser funktionieren"
      },
      {
        "type": "Fix",
        "change": "Punkte von Kommentaren noch an einigen weitern Stellen versteckt"
      },
      {
        "type": "Fix",
        "change": "App-Stack korrigiert, wenn die App über eine Benachrichtigung geöffnet wird"
      },
      {
        "type": "Fix",
        "change": "Wake Lock während Bilder vorgeladen werden"
      },
      {
        "type": "Fix",
        "change": "Ein paar Crashes gefixt"
      }
    ]
  },
  {
    "version": 76,
    "changes": [
      {
        "type": "Neu",
        "change": "@Name in Kommentaren wird nun verlinkt"
      },
      {
        "type": "Fix",
        "change": "Links zu Posts wie auf der Website gekürzt"
      },
      {
        "type": "Fix",
        "change": "Download unter Android 6 gefixt"
      },
      {
        "type": "Fix",
        "change": "Kommentarbenis wie auf pr0gramm für 60min verstecken"
      },
      {
        "type": "Fix",
        "change": "Der Start-Button für Videos funktioniert nun auch im Vollbild"
      },
      {
        "type": "Fix",
        "change": "'Vertical Video Syndrom'-Videos werden im Vollbild nicht mehr gedreht"
      },
      {
        "type": "Fix",
        "change": "Vollbild versteckt nun auch die Toolbar"
      },
      {
        "type": "Fix",
        "change": "Rotation wird im Vollbildmodus geblockt"
      },
      {
        "type": "Fix",
        "change": "Sortierung für die Kontrovers-Kategorie korrigiert"
      }
    ]
  },
  {
    "version": 75,
    "changes": [
      {
        "type": "Exklusiv & Neu",
        "change": "Neue 'Best of'-Kategorie, die nur Bilder ab einem bestimmten Benis anzeigt. In den Einstellungen konfigurierbar."
      },
      {
        "type": "Neu",
        "change": "Vollbild-Modus für Videos. Falls es nicht geht, bitte Feedback über die Feedback-Funktion!"
      }
    ]
  },
  {
    "version": 74,
    "changes": [
      {
        "type": "ACHTUNG!!!",
        "change": "Durch ein paar Updates der Libraries, bitte mal probieren und berichten, ob Uploads noch funktionieren!"
      },
      {
        "type": "Exklusiv",
        "change": "Neue Kategorie 'Kontrovers', die Bilder anzeigt, die ein ähnliches Verhältnis von Up- Down-Votes haben"
      },
      {
        "type": "Neu",
        "change": "Stelz-Kategorie kann nun ausgeblendet werden"
      },
      {
        "type": "Fix",
        "change": "Feedbackfunktion wieder repariert"
      },
      {
        "type": "Fix",
        "change": "Reposts nicht in kontrovers anzeigen"
      },
      {
        "type": "Fix",
        "change": "Herunterwischen/Neuladen auf einem Post startet das Video/GIF neu"
      },
      {
        "type": "Hinter den Kulissen",
        "change": "Viele Updates in den Abhängigkeiten, hoffe alles läuft stabil!"
      }
    ]
  },
  {
    "version": 73,
    "changes": [
      {
        "type": "Exklusiv",
        "change": "Neue Kategorie 'random', die zufällige Bilder aus dem pr0gramm ausgräbt"
      },
      {
        "type": "Neu",
        "change": "Vorschau bei Nachrichten/Antwort-Benachrichtigung"
      },
      {
        "type": "Neu",
        "change": "Markiere vorgeladene Bilder im Feed"
      },
      {
        "type": "Fix",
        "change": "Klickt man in der 'Zufall'-Kategorie Tags oder User an, wird man zu Neu weitergeleitet."
      }
    ]
  },
  {
    "version": 72,
    "changes": [
      {
        "type": "Neu",
        "change": "Fortschrittsanzeige unter Videos (in den Einstellungen deaktivierbar)"
      },
      {
        "type": "Neu",
        "change": "Hinweis bei 'Musste scrollen' Bilder auf Qualitätseinstellungen"
      },
      {
        "type": "Neu",
        "change": "Neuladen durch Herunterwischen startet Video/GIF von vorne neu"
      },
      {
        "type": "Fix",
        "change": "Download und Teilen von vorgeladenen Bildern wieder möglich"
      },
      {
        "type": "Fix",
        "change": "Bugfixes für Übersetzungen"
      }
    ]
  },
  {
    "version": 71,
    "changes": [
      {
        "type": "Neu",
        "change": "Das viel gewünschte 'preloading' ist nun endlich möglich!"
      },
      {
        "type": "Neu",
        "change": "Einstellung, ob mobil Bilder und/oder Videos erst nach Bestätigung geladen werden sollen"
      },
      {
        "type": "Fix",
        "change": "Bugfixes für Übersetzungen"
      }
    ]
  },
  {
    "version": 70,
    "changes": [
      {
        "type": "Fix",
        "change": "Antwort auf einen Kommentar über die Inbox gefixt"
      },
      {
        "type": "Fix",
        "change": "Toolbar beim Scrollen wieder korrekt verstecken"
      },
      {
        "type": "Fix",
        "change": "Ein paar kleinere Bugfixes"
      }
    ]
  },
  {
    "version": 69,
    "changes": [
      {
        "type": "Neu",
        "change": "Antworten auf Kommentare und Schreiben von Nachrichten überarbeitet."
      },
      {
        "type": "Fix",
        "change": "Flackern und Färben beim Downvote von Kommentaren gefixt."
      }
    ]
  },
  {
    "version": 68,
    "changes": [
      {
        "type": "INFO",
        "change": "Häufige Abstürze hoffentlich endlich erwischt. Wenn die App noch ständig abstürzt, bitte Feedback geben."
      },
      {
        "type": "Neu",
        "change": "Benisgraph anderer Benutzer"
      },
      {
        "type": "Neu",
        "change": "Begonnen die Anzeige der Userdetails zu überarbeiten - ist noch nicht fertig!"
      },
      {
        "type": "Neu",
        "change": "Kommentare mit eigenem Downvote werden nun ausgegraut"
      },
      {
        "type": "Fix",
        "change": "Farben der Vote-Buttons an die der Website angepasst"
      },
      {
        "type": "Fix",
        "change": "Häufige Speicherfehler auf Android 4.0 Geräten hoffentlich behoben"
      },
      {
        "type": "Fix",
        "change": "Bei einigen ist die Login-Seite direkt abgeschmiert. Sollte nun funktionieren (@lolita)"
      }
    ]
  },
  {
    "version": 67,
    "changes": [
      {
        "type": "Neu",
        "change": "Neuer Softwaredekoder, der direkt die WEBMs abspielt. Im Notfall kann auf den alten MPEG Dekoder zurückgegriffen werden"
      },
      {
        "type": "Neu",
        "change": "Videos können nun direkt als Datei über WhatsApp und co geteilt werden"
      },
      {
        "type": "Neu",
        "change": "Kommentare von OP werden nach oben sortiert"
      },
      {
        "type": "Neu",
        "change": "Anzahl der ungelesenen Nachrichten wird im Drawer angezeigt"
      },
      {
        "type": "Neu",
        "change": "Neue Animation beim Wechseln von Posts"
      },
      {
        "type": "Fix",
        "change": "Die Postansicht merkt sich nun, wo du hingescrollt hast"
      },
      {
        "type": "Fix",
        "change": "Neue Nachrichten-Benachrichtigung verstecken, wenn Nachrichten gelesen wurden"
      },
      {
        "type": "Fix",
        "change": "Neue Kommentare haben nicht mehr sofort einen Benis von Zwei"
      },
      {
        "type": "Fix",
        "change": "Verschiedene Bugfixes und Crashes behoben"
      },
      {
        "type": "Fix",
        "change": "Größe der App um 200kb verringert"
      }
    ]
  },
  {
    "version": 66,
    "changes": [
      {
        "type": "Neu",
        "change": "Option um 'Neu' zur Standardansicht nach dem Starten der App zu machen"
      },
      {
        "type": "Neu",
        "change": "Repost Markierung auch direkt in einem Post"
      },
      {
        "type": "Fix",
        "change": "Zeige Posts nicht an, wenn es deren Filtereinstellungen zulassen"
      },
      {
        "type": "Fix",
        "change": "Beim Bewerten eines Kommentars wird dessen Benis aktualisiert"
      },
      {
        "type": "Fix",
        "change": "'gif to webm'-Hinweis wurde nie angezeigt sondern hat die App zum Absturz gebracht."
      }
    ]
  },
  {
    "version": 65,
    "changes": [
      {
        "type": "Neu",
        "change": "Eine neue 'SurfaceView'-Einstellung unter Kompatibilität, die *vielleicht* bei Videoproblemen hilft."
      },
      {
        "type": "Fix",
        "change": "Es werden wieder alle Kommentare unter Nachrichten angezeigt, auch Kommentare unter nsfw/nsfl Posts"
      }
    ]
  },
  {
    "version": 64,
    "changes": [
      {
        "type": "Neu",
        "change": "Bufferindicator beim Abspielen von Videos über langsame Verbindungen"
      },
      {
        "type": "Fix",
        "change": "Einige Benutzer konnten nicht voten - das geht nun wieder."
      },
      {
        "type": "Info",
        "change": "Wie du vielleicht schon mitbekommen hast, ist die App aktuell aus Google Play entfernt worden (Google der Hurensohn). Wir arbeiten dran, sie dort demnächst wieder verfügbar zu machen. Wenn du die App trotzdem weiter empfehlen möchtest, gibt es in den Einstellungen Link zur Download Website."
      }
    ]
  },
  {
    "version": 63,
    "changes": [
      {
        "type": "Neu",
        "change": "Button zum Googlen vom aktuellen Bild"
      },
      {
        "type": "Neu",
        "change": "Muzei-Plugin - Noch nicht konfigurierbar, aber läuft"
      },
      {
        "type": "Neu",
        "change": "Neuer Videoplayer (schon wieder? - Ja, und bei Problemen bitte die Feedback Funktion nutzen!)"
      },
      {
        "type": "Neu",
        "change": "Die letzten Kommentare von anderen Usern können nun betrachtet und angeklickt werden."
      },
      {
        "type": "Neu",
        "change": "Text in Kommentaren und Nachrichten kann markiert werden"
      },
      {
        "type": "Neu",
        "change": "Text-Bildchen in der Inbox Übersicht für die Absender"
      },
      {
        "type": "Neu",
        "change": "Langes dücken auf den Benis eines Posts zeigt up/down votes."
      },
      {
        "type": "Neu",
        "change": "Häufigeres Testen auf neue Nachrichten mit exponential backoff"
      },
      {
        "type": "Neu",
        "change": "'Gif zu Webm'-Konverter auf Mobile etwas beworben"
      },
      {
        "type": "Fix",
        "change": "Der 'Antworten' Button wurde teilweise fehlerhafterweise angezeigt"
      },
      {
        "type": "Fix",
        "change": "Repost-Markierungen im Feed fehlten unter bestimmten Bedingungen"
      }
    ]
  },
  {
    "version": 61,
    "changes": [
      {
        "type": "Fix",
        "change": "Links wurden nicht mehr richtig in der App geöffnet"
      },
      {
        "type": "Fix",
        "change": "Bilder wurden nicht korrekt als 'gelesen' markiert."
      }
    ]
  },
  {
    "version": 60,
    "changes": [
      {
        "type": "Neu",
        "change": "Teilen nun wahlweise direkt als Bild, als Link zum Post oder zum Bild"
      },
      {
        "type": "Neu",
        "change": "Benisgraph zeigt ein Delta zum Benis vor sieben Tagen"
      },
      {
        "type": "Fix",
        "change": "Oberfläche an vielen Stellen überarbeitet. Mehr Performance!"
      },
      {
        "type": "Fix",
        "change": "Softwaredekoder bescheunigt - Darstellung dürfte nun schneller sein"
      },
      {
        "type": "Fix",
        "change": "Layoutfehler für Jellybean und ICS behoben"
      },
      {
        "type": "Fix",
        "change": "Benachrichtigung über neue Nachrichten verschwindet, wenn man auf 'Nachrichten' in der App klickt."
      }
    ]
  },
  {
    "version": 59,
    "changes": [
      {
        "type": "Neu",
        "change": "Animation beim Öffnen eines Posts und sofortige Vorschau des Bildes, das geladen wird."
      }
    ]
  },
  {
    "version": 58,
    "changes": [
      {
        "type": "Neu",
        "change": "Ausgewählter Kommentar mit anderer Hintergrundfarbe hervorheben"
      },
      {
        "type": "Fix",
        "change": "Workaround im Logindialog für dreckige Samsung Geräte :/"
      }
    ]
  },
  {
    "version": 57,
    "changes": [
      {
        "type": "Neu",
        "change": "Überarbeiteten Loginscreen"
      },
      {
        "type": "Neu",
        "change": "Links zu Kommentaren sollten nun in die ungefähre Nähe der Kommentare springen"
      },
      {
        "type": "Neu",
        "change": "Filter in der Actionbar zu 'alle' zusammengefasst."
      },
      {
        "type": "Intern",
        "change": "Interne Umbauten."
      },
      {
        "type": "Neu",
        "change": "Aktuellen Accounttyp im Drawer anzeigen."
      }
    ]
  },
  {
    "version": 55,
    "changes": [
      {
        "type": "Neu",
        "change": "Button im Feed zum Wechseln der Filtereinstellung."
      }
    ]
  }
]
